llama_index/readers/box/__init__.py
llama_index/readers/box/BoxAPI/__init.py__
llama_index/readers/box/BoxAPI/box_api.py
llama_index/readers/box/BoxAPI/box_llama_adaptors.py
llama_index/readers/box/BoxReader/README.md
llama_index/readers/box/BoxReader/__init__.py
llama_index/readers/box/BoxReader/base.py
llama_index/readers/box/BoxReaderAIExtraction/README.md
llama_index/readers/box/BoxReaderAIExtraction/__init__.py
llama_index/readers/box/BoxReaderAIExtraction/base.py
llama_index/readers/box/BoxReaderAIPrompt/README.md
llama_index/readers/box/BoxReaderAIPrompt/__init__.py
llama_index/readers/box/BoxReaderAIPrompt/base.py
llama_index/readers/box/BoxReaderTextExtraction/README.md
llama_index/readers/box/BoxReaderTextExtraction/__init__.py
llama_index/readers/box/BoxReaderTextExtraction/base.py
llama_index_readers_box-0.4.1.dist-info/METADATA
llama_index_readers_box-0.4.1.dist-info/WHEEL
llama_index_readers_box-0.4.1.dist-info/licenses/LICENSE
llama_index_readers_box-0.4.1.dist-info/RECORD
