Metadata-Version: 2.4
Name: llama-index-readers-box
Version: 0.4.1
Summary: llama-index readers box integration
Author-email: Box Developer Relations <dx@box.com>
Maintainer: barduinor, shurrey
License-Expression: MIT
License-File: LICENSE
Requires-Python: <4.0,>=3.9
Requires-Dist: box-sdk-gen>=1.5.0
Requires-Dist: llama-index-core<0.15,>=0.13.0
